CHANGES.txt
MANIFEST.in
README.txt
setup.py
js/__init__.py
js.css3mediaqueries.egg-info/PKG-INFO
js.css3mediaqueries.egg-info/SOURCES.txt
js.css3mediaqueries.egg-info/dependency_links.txt
js.css3mediaqueries.egg-info/entry_points.txt
js.css3mediaqueries.egg-info/namespace_packages.txt
js.css3mediaqueries.egg-info/not-zip-safe
js.css3mediaqueries.egg-info/requires.txt
js.css3mediaqueries.egg-info/top_level.txt
js/css3mediaqueries/__init__.py
js/css3mediaqueries/test_css3mediaqueries.txt
js/css3mediaqueries/resources/css3-mediaqueries.js