Metadata-Version: 1.1
Name: js.css3mediaqueries
Version: 0.9
Summary: Fanstatic packaging of css3-mediaqueries.js.
Home-page: https://bitbucket.org/it_spirit/js.css3mediaqueries
Author: Thomas Massmann
Author-email: thomas.massmann@it-spir.it
License: BSD
Download-URL: http://pypi.python.org/pypi/js.css3mediaqueries
Platform: UNKNOWN
